tejim/__init__.py
tejim/_data_convert.py
tejim-0.0.3.dist-info/METADATA
tejim-0.0.3.dist-info/WHEEL
tejim-0.0.3.dist-info/top_level.txt
tejim-0.0.3.dist-info/RECORD
