Metadata-Version: 2.1
Name: tejim
Version: 0.0.3
Summary: the next YAML killer!!111!!!!111!
Author-email: "Ivan \"Spaceginner\"" <ivan.demian2009@gmail.com>
Project-URL: Homepage, https://github.com/Spaceginner/tejim
Project-URL: Bug Tracker, https://github.com/Spaceginner/tejim/issues
Classifier: Programming Language :: Python :: 3
Classifier: License :: OSI Approved :: MIT License
Classifier: Operating System :: OS Independent
Requires-Python: >=3.10
